{
	"name": "bronze_unidades",
	"properties": {
		"linkedServiceName": {
			"referenceName": "dw_fuerzas_armadas_propio",
			"type": "LinkedServiceReference"
		},
		"folder": {
			"name": "bronze"
		},
		"annotations": [],
		"type": "AzureSqlTable",
		"schema": [
			{
				"name": "id_unit",
				"type": "varchar"
			},
			{
				"name": "id_brigada",
				"type": "varchar"
			},
			{
				"name": "nombre",
				"type": "varchar"
			},
			{
				"name": "codigo",
				"type": "varchar"
			},
			{
				"name": "ciudad",
				"type": "varchar"
			},
			{
				"name": "departamento",
				"type": "varchar"
			},
			{
				"name": "tipo_cuartel",
				"type": "varchar"
			}
		],
		"typeProperties": {
			"schema": "bronze",
			"table": "tbl_unidades"
		}
	}
}